jupyter_kernel_hook/__init__.py
jupyter_kernel_hook/_globals.py
jupyter_kernel_hook/core.py
jupyter_kernel_hook/templates/init.py.jinja
jupyter_kernel_hook-0.1.1.dist-info/LICENSE
jupyter_kernel_hook-0.1.1.dist-info/METADATA
jupyter_kernel_hook-0.1.1.dist-info/WHEEL
jupyter_kernel_hook-0.1.1.dist-info/top_level.txt
jupyter_kernel_hook-0.1.1.dist-info/RECORD
