Metadata-Version: 2.1
Name: jupyter-kernel-hook
Version: 0.1.1
Summary: Compose simple and intuitive Jupyter server extension hooks.
Home-page: https://github.com/ryxcommar/jupyter_kernel_hook
Author: ryxcommar
Author-email: ryxcommar@gmail.com
License: MIT
Platform: UNKNOWN
Classifier: Development Status :: 1 - Planning
Classifier: Environment :: Plugins
Classifier: Intended Audience :: Science/Research
Classifier: License :: OSI Approved :: BSD License
Classifier: Operating System :: OS Independent
Classifier: Topic :: Scientific/Engineering
Classifier: Programming Language :: Python :: 3
Classifier: Programming Language :: Python :: 3.6
Classifier: Programming Language :: Python :: 3.7
Classifier: Programming Language :: Python :: 3.8
Classifier: Programming Language :: Python :: 3.9
Classifier: Programming Language :: Python :: 3.10
Requires-Python: >=3.6
License-File: LICENSE
Requires-Dist: IPython
Requires-Dist: notebook
Requires-Dist: jinja2
Requires-Dist: dataclasses (>=0.6) ; python_version < "3.7"
